abnosql/__init__.py
abnosql/cli.py
abnosql/exceptions.py
abnosql/kms.py
abnosql/plugin.py
abnosql/table.py
abnosql/version.py
abnosql/mocks/__init__.py
abnosql/mocks/mock_azure_auth.py
abnosql/mocks/mock_azure_kms.py
abnosql/mocks/mock_cosmos.py
abnosql/mocks/mock_dynamodbx.py
abnosql/plugins/__init__.py
abnosql/plugins/kms/__init__.py
abnosql/plugins/kms/aws.py
abnosql/plugins/kms/azure.py
abnosql/plugins/kms/gcp.py
abnosql/plugins/table/__init__.py
abnosql/plugins/table/cosmos.py
abnosql/plugins/table/dynamodb.py
abnosql/plugins/table/firestore.py
abnosql/plugins/table/memory.py
abnosql-0.0.27.dist-info/LICENSE
abnosql-0.0.27.dist-info/METADATA
abnosql-0.0.27.dist-info/WHEEL
abnosql-0.0.27.dist-info/entry_points.txt
abnosql-0.0.27.dist-info/top_level.txt
abnosql-0.0.27.dist-info/RECORD
