Metadata-Version: 2.1
Name: abnosql
Version: 0.0.27
Summary: NoSQL Abstraction Library
Home-page: https://github.com/rog555/abnosql
Download-URL: http://pypi.python.org/pypi/abnosql
Author: Roger Foskett
Author-email: r_foskett@hotmail.com
Maintainer: Roger Foskett
Maintainer-email: r_foskett@hotmail.com
License: MIT
Keywords: nosql,azure cosmos,aws dynamodb
Platform: any
Classifier: Development Status :: 4 - Beta
Classifier: Intended Audience :: Developers
Classifier: Programming Language :: Python :: 3.9
Classifier: Programming Language :: Python :: 3.10
Classifier: Programming Language :: Python :: 3.11
Classifier: License :: OSI Approved :: MIT License
Classifier: Operating System :: OS Independent
Classifier: Topic :: System :: Distributed Computing
Classifier: Topic :: Database :: Front-Ends
Classifier: Typing :: Typed
Requires-Python: >=3.9,<4.0
License-File: LICENSE
Requires-Dist: jsonschema
Requires-Dist: pluggy
Requires-Dist: pyyaml
Requires-Dist: sqlglot
Provides-Extra: aws
Requires-Dist: boto3; extra == "aws"
Requires-Dist: botocore; extra == "aws"
Requires-Dist: dynamodb-json; extra == "aws"
Requires-Dist: aws-encryption-sdk; extra == "aws"
Provides-Extra: aws-kms
Requires-Dist: aws-encryption-sdk; extra == "aws-kms"
Requires-Dist: botocore; extra == "aws-kms"
Provides-Extra: azure
Requires-Dist: azure-cosmos; extra == "azure"
Requires-Dist: azure-identity; extra == "azure"
Requires-Dist: azure-core; extra == "azure"
Requires-Dist: azure-keyvault-keys; extra == "azure"
Requires-Dist: cryptography; extra == "azure"
Provides-Extra: azure-kms
Requires-Dist: azure-core; extra == "azure-kms"
Requires-Dist: azure-identity; extra == "azure-kms"
Requires-Dist: azure-keyvault-keys; extra == "azure-kms"
Requires-Dist: cryptography; extra == "azure-kms"
Provides-Extra: cli
Requires-Dist: click; extra == "cli"
Requires-Dist: tabulate; extra == "cli"
Provides-Extra: cosmos
Requires-Dist: azure-cosmos; extra == "cosmos"
Requires-Dist: azure-identity; extra == "cosmos"
Provides-Extra: dev
Requires-Dist: jsonschema; extra == "dev"
Requires-Dist: pluggy; extra == "dev"
Requires-Dist: pyyaml; extra == "dev"
Requires-Dist: sqlglot; extra == "dev"
Requires-Dist: click; extra == "dev"
Requires-Dist: tabulate; extra == "dev"
Requires-Dist: boto3; extra == "dev"
Requires-Dist: botocore; extra == "dev"
Requires-Dist: dynamodb-json; extra == "dev"
Requires-Dist: aws-encryption-sdk; extra == "dev"
Requires-Dist: azure-cosmos; extra == "dev"
Requires-Dist: azure-identity; extra == "dev"
Requires-Dist: azure-core; extra == "dev"
Requires-Dist: azure-keyvault-keys; extra == "dev"
Requires-Dist: cryptography; extra == "dev"
Requires-Dist: google-api-core; extra == "dev"
Requires-Dist: google-auth; extra == "dev"
Requires-Dist: google-cloud-firestore; extra == "dev"
Requires-Dist: tink[gcpkms]; extra == "dev"
Requires-Dist: responses; extra == "dev"
Requires-Dist: coverage; extra == "dev"
Requires-Dist: moto==5.0.5; extra == "dev"
Requires-Dist: mock-firestore==0.11.0; extra == "dev"
Requires-Dist: mypy; extra == "dev"
Requires-Dist: pytest; extra == "dev"
Requires-Dist: pytest-cov; extra == "dev"
Requires-Dist: pdoc; extra == "dev"
Requires-Dist: pre-commit; extra == "dev"
Provides-Extra: dynamodb
Requires-Dist: boto3; extra == "dynamodb"
Requires-Dist: botocore; extra == "dynamodb"
Requires-Dist: dynamodb-json; extra == "dynamodb"
Provides-Extra: firestore
Requires-Dist: google-api-core; extra == "firestore"
Requires-Dist: google-auth; extra == "firestore"
Requires-Dist: google-cloud-firestore; extra == "firestore"
Requires-Dist: sqlglot; extra == "firestore"
Provides-Extra: gcp
Requires-Dist: google-api-core; extra == "gcp"
Requires-Dist: google-auth; extra == "gcp"
Requires-Dist: google-cloud-firestore; extra == "gcp"
Requires-Dist: sqlglot; extra == "gcp"
Requires-Dist: tink[gcpkms]; extra == "gcp"
Provides-Extra: gcp-kms
Requires-Dist: tink[gcpkms]; extra == "gcp-kms"
Provides-Extra: google
Requires-Dist: google-api-core; extra == "google"
Requires-Dist: google-auth; extra == "google"
Requires-Dist: google-cloud-firestore; extra == "google"
Requires-Dist: sqlglot; extra == "google"
Requires-Dist: tink[gcpkms]; extra == "google"
Provides-Extra: test
Requires-Dist: jsonschema; extra == "test"
Requires-Dist: pluggy; extra == "test"
Requires-Dist: pyyaml; extra == "test"
Requires-Dist: sqlglot; extra == "test"
Requires-Dist: click; extra == "test"
Requires-Dist: tabulate; extra == "test"
Requires-Dist: boto3; extra == "test"
Requires-Dist: botocore; extra == "test"
Requires-Dist: dynamodb-json; extra == "test"
Requires-Dist: aws-encryption-sdk; extra == "test"
Requires-Dist: azure-cosmos; extra == "test"
Requires-Dist: azure-identity; extra == "test"
Requires-Dist: azure-core; extra == "test"
Requires-Dist: azure-keyvault-keys; extra == "test"
Requires-Dist: cryptography; extra == "test"
Requires-Dist: google-api-core; extra == "test"
Requires-Dist: google-auth; extra == "test"
Requires-Dist: google-cloud-firestore; extra == "test"
Requires-Dist: tink[gcpkms]; extra == "test"
Requires-Dist: responses; extra == "test"
Requires-Dist: coverage; extra == "test"
Requires-Dist: moto==5.0.5; extra == "test"
Requires-Dist: mock-firestore==0.11.0; extra == "test"
Requires-Dist: mypy; extra == "test"
Requires-Dist: pytest; extra == "test"
Requires-Dist: pytest-cov; extra == "test"
